odoo8_addon_hr_timesheet_invoice_hide_to_invoice-8.0.1.0.0.99.dev12-py2.7-nspkg.pth
odoo8_addon_hr_timesheet_invoice_hide_to_invoice-8.0.1.0.0.99.dev12.dist-info/METADATA
odoo8_addon_hr_timesheet_invoice_hide_to_invoice-8.0.1.0.0.99.dev12.dist-info/RECORD
odoo8_addon_hr_timesheet_invoice_hide_to_invoice-8.0.1.0.0.99.dev12.dist-info/WHEEL
odoo8_addon_hr_timesheet_invoice_hide_to_invoice-8.0.1.0.0.99.dev12.dist-info/namespace_packages.txt
odoo8_addon_hr_timesheet_invoice_hide_to_invoice-8.0.1.0.0.99.dev12.dist-info/top_level.txt
odoo_addons/hr_timesheet_invoice_hide_to_invoice/README.rst
odoo_addons/hr_timesheet_invoice_hide_to_invoice/__init__.py
odoo_addons/hr_timesheet_invoice_hide_to_invoice/__openerp__.py
odoo_addons/hr_timesheet_invoice_hide_to_invoice/i18n/hr_timesheet_invoice_hide_to_invoice.pot
odoo_addons/hr_timesheet_invoice_hide_to_invoice/i18n/sl.po
odoo_addons/hr_timesheet_invoice_hide_to_invoice/security/hr_timesheet_invoice_hide_to_invoice_security.xml
odoo_addons/hr_timesheet_invoice_hide_to_invoice/static/description/icon.png
odoo_addons/hr_timesheet_invoice_hide_to_invoice/views/hr_timesheet_invoice_hide_to_invoice_view.xml
